PIL-stubs/BdfFontFile.pyi
PIL-stubs/BlpImagePlugin.pyi
PIL-stubs/BmpImagePlugin.pyi
PIL-stubs/BufrStubImagePlugin.pyi
PIL-stubs/ContainerIO.pyi
PIL-stubs/CurImagePlugin.pyi
PIL-stubs/DcxImagePlugin.pyi
PIL-stubs/DdsImagePlugin.pyi
PIL-stubs/EpsImagePlugin.pyi
PIL-stubs/ExifTags.pyi
PIL-stubs/FitsImagePlugin.pyi
PIL-stubs/FliImagePlugin.pyi
PIL-stubs/FontFile.pyi
PIL-stubs/FpxImagePlugin.pyi
PIL-stubs/FtexImagePlugin.pyi
PIL-stubs/GbrImagePlugin.pyi
PIL-stubs/GdImageFile.pyi
PIL-stubs/GifImagePlugin.pyi
PIL-stubs/GimpGradientFile.pyi
PIL-stubs/GimpPaletteFile.pyi
PIL-stubs/GribStubImagePlugin.pyi
PIL-stubs/Hdf5StubImagePlugin.pyi
PIL-stubs/IcnsImagePlugin.pyi
PIL-stubs/IcoImagePlugin.pyi
PIL-stubs/ImImagePlugin.pyi
PIL-stubs/Image.pyi
PIL-stubs/ImageChops.pyi
PIL-stubs/ImageCms.pyi
PIL-stubs/ImageColor.pyi
PIL-stubs/ImageDraw.pyi
PIL-stubs/ImageDraw2.pyi
PIL-stubs/ImageEnhance.pyi
PIL-stubs/ImageFile.pyi
PIL-stubs/ImageFilter.pyi
PIL-stubs/ImageFont.pyi
PIL-stubs/ImageGrab.pyi
PIL-stubs/ImageMath.pyi
PIL-stubs/ImageMode.pyi
PIL-stubs/ImageMorph.pyi
PIL-stubs/ImageOps.pyi
PIL-stubs/ImagePalette.pyi
PIL-stubs/ImagePath.pyi
PIL-stubs/ImageQt.pyi
PIL-stubs/ImageSequence.pyi
PIL-stubs/ImageShow.pyi
PIL-stubs/ImageStat.pyi
PIL-stubs/ImageTk.pyi
PIL-stubs/ImageTransform.pyi
PIL-stubs/ImageWin.pyi
PIL-stubs/ImtImagePlugin.pyi
PIL-stubs/IptcImagePlugin.pyi
PIL-stubs/Jpeg2KImagePlugin.pyi
PIL-stubs/JpegImagePlugin.pyi
PIL-stubs/JpegPresets.pyi
PIL-stubs/METADATA.toml
PIL-stubs/McIdasImagePlugin.pyi
PIL-stubs/MicImagePlugin.pyi
PIL-stubs/MpegImagePlugin.pyi
PIL-stubs/MpoImagePlugin.pyi
PIL-stubs/MspImagePlugin.pyi
PIL-stubs/PSDraw.pyi
PIL-stubs/PaletteFile.pyi
PIL-stubs/PalmImagePlugin.pyi
PIL-stubs/PcdImagePlugin.pyi
PIL-stubs/PcfFontFile.pyi
PIL-stubs/PcxImagePlugin.pyi
PIL-stubs/PdfImagePlugin.pyi
PIL-stubs/PdfParser.pyi
PIL-stubs/PixarImagePlugin.pyi
PIL-stubs/PngImagePlugin.pyi
PIL-stubs/PpmImagePlugin.pyi
PIL-stubs/PsdImagePlugin.pyi
PIL-stubs/PyAccess.pyi
types_Pillow-10.2.0.20240511.dist-info/METADATA
types_Pillow-10.2.0.20240511.dist-info/WHEEL
types_Pillow-10.2.0.20240511.dist-info/top_level.txt
types_Pillow-10.2.0.20240511.dist-info/RECORD
